Metadata-Version: 2.1
Name: glimpy
Version: 0.1.0
Summary: Generalized Linear Models in Python
Home-page: https://github.com/KSafran/glimpy
Author: Kyle Safran
Author-email: ksafran356@gmail.com
License: MIT
Download-URL: https://github.com/KSafran/glimpy/archive/0.1.0.tar.gz
Platform: UNKNOWN
Requires-Python: >=3.6
